cutesnowflakes/__init__.py
cutesnowflakes/cutesnowflakes.py
cutesnowflakes-1.0.1.dist-info/METADATA
cutesnowflakes-1.0.1.dist-info/WHEEL
cutesnowflakes-1.0.1.dist-info/top_level.txt
cutesnowflakes-1.0.1.dist-info/RECORD
