Metadata-Version: 2.1
Name: cutesnowflakes
Version: 1.0.1
Summary: Cute 3x3 images from snowflake IDs
Home-page: https://github.com/CodeBizarre/cutesnowflakes
Author: CodeBizarre
License: MIT
Platform: UNKNOWN
Classifier: License :: OSI Approved :: MIT License
Classifier: Programming Language :: Python :: 3
Classifier: Programming Language :: Python :: 3.7
Classifier: Programming Language :: Python :: 3.8
Classifier: Programming Language :: Python :: 3.9
Requires-Python: >=3.7
Requires-Dist: numpy (==1.19.3)
Requires-Dist: pillow (==8.0)
Requires-Dist: click (>=7.1<7.2)
Requires-Dist: aenum (>=2.2<2.3)
